api/__init__.py
api/endpoints/__init__.py
api/endpoints/actions.py
api/endpoints/activities.py
api/endpoints/alias.py
api/endpoints/annuaires.py
api/endpoints/buildings.py
api/endpoints/equipments.py
api/endpoints/equipments_directories.py
api/endpoints/favorites.py
api/endpoints/grafanas.py
api/endpoints/incidents.py
api/endpoints/settings.py
api/endpoints/switches.py
api/endpoints/templates.py
api/endpoints/tools.py
api/endpoints/users.py
api/server/__init__.py
api/server/auth.py
api/server/commons.py
api/server/main.py
api/server/router.py
domain/Meteo.py
domain/__init__.py
domain/activity_logs.py
domain/building.py
domain/certificate_management.py
domain/cisco_prime.py
domain/configs_management.py
domain/contact.py
domain/data_backup.py
domain/equipes.py
domain/equipment_management.py
domain/equipments_directories.py
domain/equipments_group.py
domain/favorite_links.py
domain/label.py
domain/menus.py
domain/record_dns.py
domain/script_model.py
domain/site.py
domain/switch_management.py
domain/user.py
domain/tickets/__init__.py
domain/tickets/actions.py
domain/tickets/departments.py
domain/tickets/incidents.py
domain/tools/__init__.py
domain/tools/ansible.py
domain/tools/frontend.py
domain/tools/grafana.py
domain/tools/nginx.py
domain/tools/syslog.py
output/__init__.py
output/building_ansible.py
output/contact_sheet.py
output/directories.py
output/record_dns_bind9.py
output/record_dns_infoblox.py
output/database/__init__.py
output/database/database_base.py
output/database/database_main.py
output/database/repository.py
output/external_api/__init__.py
output/external_api/cisco_prime_output.py
output/external_api/tickets/__init__.py
output/external_api/tickets/actions_impl.py
output/external_api/tickets/department_impl.py
output/external_api/tickets/incident_impl.py
output/models/__init__.py
output/models/activity_logs_database.py
output/models/building_database.py
output/models/contact_database.py
output/models/equipe_database.py
aloso-0.0.70.dist-info/METADATA
aloso-0.0.70.dist-info/WHEEL
aloso-0.0.70.dist-info/top_level.txt
aloso-0.0.70.dist-info/RECORD
