Metadata-Version: 2.1
Name: aloso
Version: 0.0.70
Summary: Lib
Author: Aleos
Author-email: aae5654ae@mozmail.com
License: MIT
Classifier: Programming Language :: Python :: 3
Classifier: License :: OSI Approved :: MIT License
Classifier: Operating System :: OS Independent
Requires-Dist: fastapi (==0.85.1)
Requires-Dist: fabric (==2.7.1)
Requires-Dist: uvicorn (==0.19.0)
Requires-Dist: pandas (==1.5.1)
Requires-Dist: openpyxl (==3.0.10)
Requires-Dist: starlette (==0.20.4)
Requires-Dist: schedule (==1.1.0)
Requires-Dist: SQLAlchemy (==2.0.16)
Requires-Dist: ldap3 (==2.9.1)
Requires-Dist: patchwork (==1.0.1)
Requires-Dist: pycryptodome (==3.17)
Requires-Dist: gunicorn (==20.1.0)
Requires-Dist: pyjwt (==2.7.0)
Requires-Dist: requests (==2.31.0)
Requires-Dist: watchdog (==3.0.0)
